{"default_CodingSensei.png":{"total_gen_time":264954,"user_word_count":12,"non_user_word_count":284,"user_msg_count":6,"non_user_msg_count":7,"total_swipe_count":0,"chat_size":19208,"date_last_chat":1707241206457,"date_first_chat":1702343340000},"default_FluxTheCat.png":{"total_gen_time":0,"user_word_count":0,"non_user_word_count":0,"user_msg_count":0,"non_user_msg_count":0,"total_swipe_count":0,"chat_size":0,"date_last_chat":0,"date_first_chat":253402300799999},"default_Seraphina.png":{"total_gen_time":0,"user_word_count":0,"non_user_word_count":147,"user_msg_count":0,"non_user_msg_count":1,"total_swipe_count":0,"chat_size":2433,"date_last_chat":1707241206493,"date_first_chat":253402300799999},"停云.png":{"total_gen_time":1873467,"user_word_count":1,"non_user_word_count":289,"user_msg_count":44,"non_user_msg_count":45,"total_swipe_count":0,"chat_size":151943,"date_last_chat":1707241206597,"date_first_chat":1704231780000},"宝宝教程Wiki 群：910524479.png":{"total_gen_time":0,"user_word_count":0,"non_user_word_count":42,"user_msg_count":0,"non_user_msg_count":1,"total_swipe_count":0,"chat_size":2674,"date_last_chat":1707241206636,"date_first_chat":253402300799999},"慕嫣然.png":{"total_gen_time":0,"user_word_count":0,"non_user_word_count":28,"user_msg_count":0,"non_user_msg_count":2,"total_swipe_count":1,"chat_size":3521,"date_last_chat":1707241206672,"date_first_chat":253402300799999},"苏郁(无法拒绝的隔壁人妻).png":{"total_gen_time":586151,"user_word_count":0,"non_user_word_count":93,"user_msg_count":15,"non_user_msg_count":18,"total_swipe_count":2,"chat_size":77260,"date_last_chat":1707241206772,"date_first_chat":1706144280000},"苏郁.png":{"total_gen_time":25734638,"user_word_count":15,"non_user_word_count":4281,"user_msg_count":297,"non_user_msg_count":309,"total_swipe_count":6,"chat_size":1566238,"date_last_chat":1707241207023,"date_first_chat":1704248400000},"苏雪卿1.png":{"total_gen_time":6649022,"user_word_count":3,"non_user_word_count":1361,"user_msg_count":68,"non_user_msg_count":144,"total_swipe_count":0,"chat_size":1606490,"date_last_chat":1707328985162,"date_first_chat":1707065220000},"触手巢穴（你是猎物）.png":{"total_gen_time":0,"user_word_count":0,"non_user_word_count":0,"user_msg_count":0,"non_user_msg_count":1,"total_swipe_count":0,"chat_size":703,"date_last_chat":1707241207428,"date_first_chat":253402300799999},"豆之RPG.png":{"total_gen_time":2074263,"user_word_count":9,"non_user_word_count":548,"user_msg_count":18,"non_user_msg_count":34,"total_swipe_count":0,"chat_size":118595,"date_last_chat":1707241207467,"date_first_chat":1702334400000},"豆之涩涩RPG[女性向].png":{"total_gen_time":0,"user_word_count":0,"non_user_word_count":6,"user_msg_count":0,"non_user_msg_count":2,"total_swipe_count":0,"chat_size":1745,"date_last_chat":1707241207535,"date_first_chat":253402300799999},"timestamp":1707328985165}